yaqd_vici/VERSION
yaqd_vici/__init__.py
yaqd_vici/__version__.py
yaqd_vici/_vici_two_position.py
yaqd_vici/vici-two-position.avpr
yaqd_vici/vici-two-position.toml
yaqd_vici-2022.8.0.dist-info/entry_points.txt
yaqd_vici-2022.8.0.dist-info/LICENSE
yaqd_vici-2022.8.0.dist-info/WHEEL
yaqd_vici-2022.8.0.dist-info/METADATA
yaqd_vici-2022.8.0.dist-info/RECORD
